[
  {
    "question_no": 1,
    "question": "એશિયન ઇન્ડોર એથ્લેટિક્સ ચેમ્પિયનશિપ્સ 2026 માં પુરુષોની હેપ્ટાથલોનમાં કોણે ગોલ્ડ મેડલ જીત્યો, જેણે 5, 993 પોઈન્ટ્સ સાથે નવો રાષ્ટ્રીય ઇન્ડોર રેકોર્ડ બનાવ્યો?",
    "options": [
      "તેજસ્વિન શંકર",
      "તજિન્દરપાલ સિંહ તૂર",
      "એન્સી સોજન",
      "પૂજા"
    ],
    "answer": "Option A: તેજસ્વિન શંકર",
    "explanation": "તેજસ્વિન શંકરે તિયાનજિનમાં યોજાયેલી એશિયન ઇન્ડોર એથ્લેટિક્સ ચેમ્પિયનશિપ 2026માં પુરુષોની હેપ્ટાથલોનમાં ઐતિહાસિક ગોલ્ડ મેડલ મેળવ્યો હતો. તેણે 5, 993 પોઈન્ટ્સ એકઠા કર્યા, એક નવો રાષ્ટ્રીય ઇન્ડોર રેકોર્ડ સ્થાપિત કર્યો અને 2021 માં સેટ કરેલા તેના અગાઉના સર્વશ્રેષ્ઠ 5, 650 પોઈન્ટ્સને પાછળ છોડી દીધા. તેના પ્રદર્શનથી ચેમ્પિયનશિપમાં ભારતનો એકમાત્ર સુવર્ણ ચંદ્રક નોંધાયો હતો અને દેશને પાંચ ચંદ્રકો સાથે એકંદરે છઠ્ઠા સ્થાને રહેવામાં મહત્વની ભૂમિકા ભજવી હતી. આ સિદ્ધિ કોન્ટિનેંટલ સ્ટેજ પર મલ્ટી-ઇવેન્ટ એથ્લેટિક્સમાં ભારતની વધતી જતી તાકાતને દર્શાવે છે.",
    "category": "Sports",
    "date": "2026-02-18"
  },
  {
    "question_no": 2,
    "question": "જાહેર ક્ષેત્રની કઈ બેંકે 15-દિવસની સમયરેખા સાથે ઓનલાઈન ડેથ ક્લેઈમ સેટલમેન્ટ પોર્ટલ લોન્ચ કર્યું અને ₹15 lakh સુધીના દાવાઓ માટે કોઈ જામીનની આવશ્યકતા નથી?",
    "options": [
      "પંજાબ નેશનલ બેંક",
      "બેંક ઓફ બરોડા",
      "ઈન્ડિયન ઓવરસીઝ બેંક",
      "કેનેરા બેંક"
    ],
    "answer": "Option C: ઈન્ડિયન ઓવરસીઝ બેંક",
    "explanation": "ઇન્ડિયન ઓવરસીઝ બેંકે પરિવારો અને કાનૂની વારસદારો માટે એક સરળ, પારદર્શક અને સમયબદ્ધ ઉકેલ પૂરો પાડવા માટે ઓનલાઈન ડેથ ક્લેમ સેટલમેન્ટ પોર્ટલ રજૂ કર્યું છે. ડિજીટલ પ્લેટફોર્મ દાવેદારની વિગતો, દસ્તાવેજ અપલોડ અને દાવાની સ્થિતિનું રીઅલ-ટાઇમ ટ્રેકિંગ, પુનરાવર્તિત શાખા મુલાકાતોની જરૂરિયાતને દૂર કરીને ઑનલાઇન સબમિશનને સક્ષમ કરે છે. ₹15 lakh સુધીના દાવાઓ માટે, બેંકે 15 દિવસની અંદર પતાવટની ખાતરી કરીને, તૃતીય-પક્ષ જામીનની જરૂરિયાત અને દસ્તાવેજીકરણમાં ઘટાડો કર્યો છે. આ પહેલની સાથે, બેંકે એક નવી કોર્પોરેટ વેબસાઈટ પણ લોન્ચ કરી છે, જે કરુણાપૂર્ણ, ગ્રાહક-કેન્દ્રિત અભિગમ જાળવી રાખીને ડિજિટલ પરિવર્તન માટે તેની પ્રતિબદ્ધતાને મજબૂત બનાવે છે.",
    "category": "Banking",
    "date": "2026-02-18"
  },
  {
    "question_no": 3,
    "question": "ટેલિકોમ, ડિજિટલ અર્થતંત્ર અને ઉભરતી ટેક્નોલોજીમાં સહકાર વધારવા માટે કયા દેશે ભારત સાથે વાતચીત કરી?",
    "options": [
      "આયર્લેન્ડ",
      "જર્મની",
      "ઓસ્ટ્રેલિયા",
      "જાપાન"
    ],
    "answer": "Option A: આયર્લેન્ડ",
    "explanation": "ટેલિકોમ અને ઉભરતી ટેક્નોલોજીમાં સહયોગને મજબૂત કરવા માટે ભારતે આયર્લેન્ડ સાથે ઉચ્ચ સ્તરીય ચર્ચા કરી. આ વાટાઘાટોમાં કેન્દ્રીય મંત્રી જ્યોતિરાદિત્ય સિંધિયા અને આયર્લેન્ડના જેક ચેમ્બર્સ સામેલ હતા, જેમાં નવીનતા આધારિત ભાગીદારી પર ધ્યાન કેન્દ્રિત કર્યું હતું. મુખ્ય ક્ષેત્રોમાં ભારતના ડિજિટલ પબ્લિક ઇન્ફ્રાસ્ટ્રક્ચરનો સમાવેશ થાય છે, જેમ કે UPI અને DBT, ઝડપી 5G વિસ્તરણ અને ગ્રામીણ બ્રોડબેન્ડ વિકાસ. બંને રાષ્ટ્રોએ ક્વોન્ટમ કોમ્યુનિકેશન્સ, આર્ટિફિશિયલ ઈન્ટેલિજન્સ અને રેગ્યુલેટરી ઈનોવેશન જેવા અદ્યતન ક્ષેત્રોમાં સહયોગી તકોની પણ શોધ કરી, જે ટેક્નોલોજી અને ડિજિટલ ટ્રાન્સફોર્મેશન પહેલ દ્વારા દ્વિપક્ષીય સંબંધોને વધુ ગાઢ બનાવવાની તેમની સહિયારી પ્રતિબદ્ધતાને દર્શાવે છે.",
    "category": "International",
    "date": "2026-02-18"
  },
  {
    "question_no": 4,
    "question": "ભારતને મહિલા વિશ્વ કપમાં ઐતિહાસિક જીત અપાવ્યા બાદ કોને BBC ઇન્ડિયન સ્પોર્ટ્સવુમન ઓફ ધ યર 2025 નામ આપવામાં આવ્યું હતું?",
    "options": [
      "દિવ્યા દેશમુખ",
      "સ્મૃતિ મંધાના",
      "પ્રીતિ પાલ",
      "અંજલિ ભાગવત"
    ],
    "answer": "Option B: સ્મૃતિ મંધાના",
    "explanation": "સ્મૃતિ મંધાનાને તેમના અસાધારણ નેતૃત્વ અને પ્રદર્શનની માન્યતામાં BBC ભારતીય સ્પોર્ટ્સવુમન ઓફ ધ યર 2025 તરીકે સન્માનિત કરવામાં આવી હતી. તેણીએ ભારતને ઐતિહાસિક મહિલા વિશ્વ કપ વિજય માટે માર્ગદર્શન આપ્યું, જે ભારતીય મહિલા ક્રિકેટમાં એક મહત્વપૂર્ણ સીમાચિહ્નરૂપ છે. અન્ય નોંધપાત્ર દાવેદારોમાં ચેસ વર્લ્ડ કપ વિજેતા દિવ્યા દેશમુખ અને પેરાલિમ્પિક મેડલ વિજેતા પ્રીતિ પાલનો સમાવેશ થાય છે. વેટરન શૂટર અંજલિ ભાગવતને લાઈફટાઈમ અચીવમેન્ટ એવોર્ડ મળ્યો હતો, જેણે ભારતીય શૂટિંગ સ્પોર્ટ્સમાં તેમના લાંબા ગાળાના યોગદાનને હાઈલાઈટ કર્યું હતું.",
    "category": "Sports",
    "date": "2026-02-18"
  },
  {
    "question_no": 5,
    "question": "કયા શહેરે 23મી બાયોએશિયા 2026 સમિટનું આયોજન કર્યું હતું?",
    "options": [
      "હૈદરાબાદ",
      "બેંગલુરુ",
      "ચેન્નાઈ",
      "પુણે"
    ],
    "answer": "Option A: હૈદરાબાદ",
    "explanation": "23મી બાયોએશિયા 2026 સમિટનું ઉદ્ઘાટન હૈદરાબાદમાં તેલંગાણાના મુખ્યમંત્રી એ. રેવન્ત રેડ્ડીએ કર્યું હતું. સમિટ, થીમ આધારિત 'TechBio અનલીશ્ડ - AI, ઓટોમેશન, અને જીવન વિજ્ઞાનમાં ક્રાંતિકારી ફેરફારો', વૈશ્વિક નિષ્ણાતો અને ઉદ્યોગ નેતાઓને એકસાથે લાવ્યા. બે દિવસમાં, સહભાગીઓએ AI-સંચાલિત સંશોધન અને વિકાસ, નેક્સ્ટ જનરેશન બાયોલોજીક્સ, ડિજિટલ ટ્રાન્સફોર્મેશન અને જીવન વિજ્ઞાનના વિકસતા ભાવિ વિશે ચર્ચા કરી. આ ઇવેન્ટમાં 2047 દ્વારા વિશ્વ-કક્ષાના બાયોફાર્મા હબ તરીકે સ્થાન મેળવવા માટે તેલંગાણાના વ્યૂહાત્મક દ્રષ્ટિકોણને પણ પ્રકાશિત કરવામાં આવ્યો હતો, જે બાયોટેક્નોલોજી અને ફાર્માસ્યુટિકલ ઇનોવેશનમાં તેની વધતી જતી આગવી ઓળખને વધુ મજબૂત બનાવે છે.",
    "category": "Places",
    "date": "2026-02-18"
  },
  {
    "question_no": 6,
    "question": "કયા શહેરમાં ડેમ સેફ્ટી 2026 પર આંતરરાષ્ટ્રીય પરિષદ યોજાઈ હતી, જેમાં વૈશ્વિક નિષ્ણાતો અને નિયમનકારોને એકસાથે લાવવામાં આવ્યા હતા?",
    "options": [
      "હૈદરાબાદ",
      "ચેન્નાઈ",
      "મુંબઈ",
      "બેંગલુરુ"
    ],
    "answer": "Option D: બેંગલુરુ",
    "explanation": "ડેમ મેનેજમેન્ટ અને જળ સંસાધનોના ક્ષેત્રમાં વૈશ્વિક નિષ્ણાતો, નિયમનકારો અને પ્રેક્ટિશનરોને આકર્ષિત કરતી ડેમ સેફ્ટી 2026 પરની આંતરરાષ્ટ્રીય પરિષદ બેંગલુરુમાં પૂર્ણ થઈ હતી. કોન્ફરન્સમાં ડેમ સેફ્ટી એક્ટ, 2021 અને ડેમ રિહેબિલિટેશન એન્ડ ઇમ્પ્રૂવમેન્ટ પ્રોજેક્ટ (DRIP) હેઠળ સંસ્થાકીય અને તકનીકી માળખાને મજબૂત કરવા પર ધ્યાન કેન્દ્રિત કરવામાં આવ્યું હતું. મુખ્ય ચર્ચાઓ વૃદ્ધ ડેમના પુનર્વસન, કાંપ વ્યવસ્થાપન વ્યૂહરચનાઓ, વાસ્તવિક સમયની દેખરેખ પ્રણાલી, જોખમ આધારિત નિર્ણય લેવાની, સંકલિત પૂર કામગીરી અને આબોહવા સ્થિતિસ્થાપકતા વધારવાની આસપાસ ફરતી હતી, જે ડેમની સલામતી અને ટકાઉ જળ માળખાકીય વ્યવસ્થાપન સુનિશ્ચિત કરવા માટે ભારતની પ્રતિબદ્ધતાને પ્રતિબિંબિત કરે છે.",
    "category": "National",
    "date": "2026-02-18"
  },
  {
    "question_no": 7,
    "question": "કર્ણાટકમાં હેલિકોપ્ટર એસેમ્બલી લાઇન સ્થાપિત કરવા માટે વડા પ્રધાન નરેન્દ્ર મોદી અને રાષ્ટ્રપતિ ઇમેન્યુઅલ મેક્રોન દ્વારા કઈ પહેલ શરૂ કરવામાં આવી હતી?",
    "options": [
      "C295 એરક્રાફ્ટ પ્રોજેક્ટ",
      "તેજસ Mk2 પ્રોગ્રામ",
      "ધ્રુવ વિસ્તરણ મિશન",
      "H125 પ્રોજેક્ટ"
    ],
    "answer": "Option D: H125 પ્રોજેક્ટ",
    "explanation": "H125 પ્રોજેક્ટ નરેન્દ્ર મોદી અને ઈમેન્યુઅલ મેક્રોન દ્વારા અપગ્રેડેડ ભારત-ફ્રાન્સ ભાગીદારીના ભાગરૂપે લોન્ચ કરવામાં આવ્યો હતો. આ પહેલ કર્ણાટકમાં ભારતની પ્રથમ ખાનગી-ક્ષેત્રની હેલિકોપ્ટર ઉત્પાદન સુવિધા સ્થાપે છે, જેમાં H125 હેલિકોપ્ટર માટેની અંતિમ એસેમ્બલી લાઇન છે. આ પ્રોજેક્ટ સ્થાનિક ઉત્પાદન અને નિકાસને સમર્થન આપે છે, જેની પ્રારંભિક ક્ષમતા દર વર્ષે 10 હેલિકોપ્ટરની છે. માઉન્ટ એવરેસ્ટ પર ઉતરાણ સહિત તેના ઉચ્ચ-ઉંચાઈના પ્રદર્શન માટે જાણીતું, H125 નાગરિક અને સંભવિત લશ્કરી જરૂરિયાતો પૂરી કરશે, ભારતના આત્મનિર્ભર ભારત મિશનને મજબૂત કરશે અને બંને રાષ્ટ્રો વચ્ચે વ્યૂહાત્મક એરોસ્પેસ સહયોગને વધુ ગાઢ બનાવશે.",
    "category": "Defence",
    "date": "2026-02-18"
  },
  {
    "question_no": 8,
    "question": "કયું ભારતીય રાજ્ય 1, 750 MW ડેમવે લોઅર હાઇડલ પ્રોજેક્ટનું ઘર છે જેને તાજેતરમાં 2037 સુધી પર્યાવરણીય મંજૂરી એક્સ્ટેંશન મળી છે?",
    "options": [
      "સિક્કિમ",
      "અરુણાચલ પ્રદેશ",
      "હિમાચલ પ્રદેશ",
      "ઉત્તરાખંડ"
    ],
    "answer": "Option B: અરુણાચલ પ્રદેશ",
    "explanation": "અરુણાચલ પ્રદેશ લોહિત નદી પર સ્થિત 1, 750 MW ડેમવે લોઅર હાઇડલ પ્રોજેક્ટનું આયોજન કરે છે. પ્રોજેક્ટને પર્યાવરણીય મંજૂરીનું 11-વર્ષનું વિસ્તરણ મંજૂર કરવામાં આવ્યું છે, જે કામગીરીને 2037 સુધી ચાલુ રાખવાની મંજૂરી આપે છે. મુકદ્દમામાં વિલંબને ધ્યાનમાં લીધા બાદ પર્યાવરણ મંત્રાલય હેઠળની નિષ્ણાત મૂલ્યાંકન સમિતિ દ્વારા મંજૂરી આપવામાં આવી હતી. જો કે, પર્યાવરણીય રીતે સંવેદનશીલ લોહિત બેસિન પ્રદેશમાં વન્યજીવન મંજૂરી અને જૈવવિવિધતાની ચિંતાઓ અંગે નેશનલ ગ્રીન ટ્રિબ્યુનલ દ્વારા અગાઉના હસ્તક્ષેપને કારણે વિસ્તરણ ચર્ચાનું કારણ બન્યું છે.",
    "category": "State",
    "date": "2026-02-18"
  },
  {
    "question_no": 9,
    "question": "કન્ઝ્યુમર ગૂડ્ઝ કંપનીઓમાં રિટેલ એક્ઝિક્યુશન અને બ્રાન્ડ પરિપૂર્ણતા વધારવા માટે કયા ઝડપી વાણિજ્ય પ્લેટફોર્મે બિઝોમ સાથે ભાગીદારી કરી?",
    "options": [
      "સ્વિગી ઇન્સ્ટામાર્ટ",
      "ઝેપ્ટો",
      "બ્લિન્કિટ",
      "બિગબાસ્કેટ"
    ],
    "answer": "Option C: બ્લિન્કિટ",
    "explanation": "Bizom એ રિટેલ એક્ઝિક્યુશનને મજબૂત કરવા અને બ્રાન્ડ પરિપૂર્ણતા ક્ષમતાઓને સુધારવા માટે Blinkit સાથે વ્યૂહાત્મક ભાગીદારીમાં પ્રવેશ કર્યો. આ સહયોગ બ્રાન્ડ્સને પરિપૂર્ણતાની ઝડપ વધારવા, સ્ટોક-આઉટ ઘટાડવા અને ઝડપી વાણિજ્ય પ્લેટફોર્મ પર એકીકૃત રીઅલ-ટાઇમ ઇન્વેન્ટરી ડેટાને ઍક્સેસ કરવા સક્ષમ બનાવે છે. ઇન્વેન્ટરી અને વેચાણની માહિતી માટે સત્યનો એક જ, વિશ્વસનીય સ્ત્રોત ઓફર કરીને, ભાગીદારી બ્રાન્ડ્સને નવી સપ્લાય ચેઇન ઇન્ફ્રાસ્ટ્રક્ચરમાં રોકાણ કર્યા વિના તેમની પહોંચ વધારવાની મંજૂરી આપે છે. આ પહેલ 750 થી વધુ કન્ઝ્યુમર ગુડ્સ કંપનીઓ માટે આયોજન અને અમલીકરણને સમર્થન આપે છે, જે સમગ્ર ભારતમાં વધુ કાર્યક્ષમ, ટેકનોલોજી આધારિત અને ભાવિ-તૈયાર રિટેલ કામગીરીમાં યોગદાન આપે છે.",
    "category": "Business",
    "date": "2026-02-18"
  },
  {
    "question_no": 10,
    "question": "કઈ સંસ્થાએ GalaxEye સાથે તેની SyncFused OptoSAR સેટેલાઇટ ઇમેજીને વૈશ્વિક સ્તરે પ્રમોટ કરવા અને વેચવા માટે ભાગીદારી કરી?",
    "options": [
      "ISRO",
      "NSIL",
      "DRDO",
      "IN-સ્પેસ"
    ],
    "answer": "Option B: NSIL",
    "explanation": "સ્પેસ સ્ટાર્ટઅપ GalaxEye એ ન્યૂસ્પેસ ઈન્ડિયા લિમિટેડ સાથે વ્યૂહાત્મક કરાર કર્યો, જેને સામાન્ય રીતે NSIL તરીકે ઓળખવામાં આવે છે, જે ભારતીય અવકાશ સંશોધન સંસ્થાના વ્યવસાયિક હાથ તરીકે કાર્ય કરે છે. આ ભાગીદારી GalaxEye ને આ પ્રકારનો ડેટા રિસેલર સહયોગ સ્થાપિત કરનાર પ્રથમ ખાનગી ભારતીય સેટેલાઇટ ઓપરેટર બનાવે છે. કરાર હેઠળ, NSIL વૈશ્વિક સ્તરે માર્કેટ કરશે અને GalaxEye ની SyncFused OptoSAR સેટેલાઇટ ઇમેજરીનું વિતરણ કરશે. સહયોગનો ઉદ્દેશ્ય કૃષિ, આપત્તિ વ્યવસ્થાપન, પર્યાવરણીય દેખરેખ અને અન્ય મહત્વપૂર્ણ એપ્લિકેશનો જેવા ક્ષેત્રો માટે ઉચ્ચ-ચોકસાઇવાળા ડેટા સોલ્યુશન્સ પ્રદાન કરવાનો છે, જે વૈશ્વિક અવકાશ-આધારિત ડેટા માર્કેટમાં ભારતની હાજરીને વધારશે.",
    "category": "Technology",
    "date": "2026-02-18"
  }
]